imgcap.py
imgcap-0.2.dist-info/METADATA
imgcap-0.2.dist-info/WHEEL
imgcap-0.2.dist-info/entry_points.txt
imgcap-0.2.dist-info/top_level.txt
imgcap-0.2.dist-info/RECORD
