Metadata-Version: 2.1
Name: imgcap
Version: 0.2
Summary: Generate captions for images using GIT from MSFT
Author: Ashvanth.S
License: Apache-2.0
Project-URL: Homepage, https://github.com/ash-01xor/Imgcap
Classifier: Development Status :: 3 - Alpha
Requires-Dist: transformers
Requires-Dist: click
Requires-Dist: torch
Requires-Dist: pillow
Requires-Dist: rich
Requires-Dist: pytest
Provides-Extra: test
Requires-Dist: pytest ; extra == 'test'
Requires-Dist: pytest-mock ; extra == 'test'
